attendance_model/VERSION
attendance_model/__init__.py
attendance_model/config.yml
attendance_model/pipeline.py
attendance_model/predict.py
attendance_model/train_pipeline.py
attendance_model/config/__init__.py
attendance_model/config/core.py
attendance_model/datasets/__init__.py
attendance_model/datasets/frequentation_dtwh.db
attendance_model/processing/__init__.py
attendance_model/processing/data_manager.py
attendance_model/processing/feature_engineering.py
attendance_model/processing/validation.py
attendance_model/trained_models/__init__.py
attendance_model/trained_models/attendance_model_output_v0.0.8.pkl
attendance_model-0.0.8.dist-info/METADATA
attendance_model-0.0.8.dist-info/WHEEL
attendance_model-0.0.8.dist-info/top_level.txt
attendance_model-0.0.8.dist-info/RECORD
